tensordict/_C.so
tensordict/__init__.py
tensordict/__init__.pyi
tensordict/_contextlib.py
tensordict/_datasets.py
tensordict/_lazy.py
tensordict/_nestedkey.py
tensordict/_nestedkey.pyi
tensordict/_pytree.py
tensordict/_reductions.py
tensordict/_td.py
tensordict/_tensorcollection.py
tensordict/_tensorcollection.pyi
tensordict/_torch_func.py
tensordict/_unbatched.py
tensordict/_version.py
tensordict/base.py
tensordict/functional.py
tensordict/memmap.py
tensordict/persistent.py
tensordict/tensorclass.py
tensordict/tensorclass.pyi
tensordict/tensordict.py
tensordict/utils.py
tensordict/_C/__init__.pyi
tensordict/_tensordict/__init__.py
tensordict/nn/__init__.py
tensordict/nn/common.py
tensordict/nn/cudagraphs.py
tensordict/nn/ensemble.py
tensordict/nn/functional_modules.py
tensordict/nn/params.py
tensordict/nn/probabilistic.py
tensordict/nn/sequence.py
tensordict/nn/tensorclass_module.py
tensordict/nn/utils.py
tensordict/nn/distributions/__init__.py
tensordict/nn/distributions/composite.py
tensordict/nn/distributions/continuous.py
tensordict/nn/distributions/discrete.py
tensordict/nn/distributions/truncated_normal.py
tensordict/nn/distributions/utils.py
tensordict/prototype/__init__.py
tensordict/prototype/fx.py
tensordict_nightly-2026.2.1.dist-info/licenses/LICENSE
tensordict_nightly-2026.2.1.dist-info/METADATA
tensordict_nightly-2026.2.1.dist-info/WHEEL
tensordict_nightly-2026.2.1.dist-info/top_level.txt
tensordict_nightly-2026.2.1.dist-info/RECORD
