Metadata-Version: 2.4
Name: tensordict-nightly
Version: 2026.2.1
Summary: TensorDict is a pytorch dedicated tensor container.
Author-email: Vincent Moens <vincentmoens@gmail.com>
License: BSD
Project-URL: homepage, https://github.com/pytorch/tensordict
Classifier: Programming Language :: Python :: 3.10
Classifier: Programming Language :: Python :: 3.11
Classifier: Programming Language :: Python :: 3.12
Classifier: Programming Language :: Python :: 3.13
Classifier: Programming Language :: Python :: 3.14
Classifier: Development Status :: 4 - Beta
Requires-Python: >=3.10
License-File: LICENSE
Requires-Dist: torch
Requires-Dist: numpy
Requires-Dist: cloudpickle
Requires-Dist: packaging
Requires-Dist: importlib_metadata
Requires-Dist: orjson; python_version < "3.13"
Requires-Dist: pyvers<0.3.0,>=0.2.0
Provides-Extra: tests
Requires-Dist: pytest; extra == "tests"
Requires-Dist: pyyaml; extra == "tests"
Requires-Dist: pytest-instafail; extra == "tests"
Requires-Dist: pytest-rerunfailures; extra == "tests"
Requires-Dist: pytest-benchmark; extra == "tests"
Provides-Extra: h5
Requires-Dist: h5py>=3.8; extra == "h5"
Provides-Extra: dev
Requires-Dist: pybind11; extra == "dev"
Requires-Dist: ninja; extra == "dev"
Provides-Extra: typecheck
Requires-Dist: mypy>=1.0.0; extra == "typecheck"
Provides-Extra: onnx
Requires-Dist: onnx; extra == "onnx"
Requires-Dist: onnxscript; extra == "onnx"
Requires-Dist: onnxruntime; extra == "onnx"
Dynamic: license-file
